nixtla/__init__.py
nixtla/client.py
nixtla/core/__init__.py
nixtla/core/api_error.py
nixtla/core/client_wrapper.py
nixtla/core/datetime_utils.py
nixtla/core/jsonable_encoder.py
nixtla/core/remove_none_from_dict.py
nixtla/errors/__init__.py
nixtla/errors/unprocessable_entity_error.py
nixtla/py.typed
nixtla/timegpt.py
nixtla/types/__init__.py
nixtla/types/http_validation_error.py
nixtla/types/multi_series_input.py
nixtla/types/single_series_forecast.py
nixtla/types/validation_error.py
nixtla/types/validation_error_loc_item.py
fern_nixtla-0.0.4.dist-info/METADATA
fern_nixtla-0.0.4.dist-info/WHEEL
fern_nixtla-0.0.4.dist-info/RECORD
